sanicargs/__init__.py
sanicargs/fields.py
sanicargs-3.0.1.dist-info/LICENSE
sanicargs-3.0.1.dist-info/METADATA
sanicargs-3.0.1.dist-info/WHEEL
sanicargs-3.0.1.dist-info/RECORD
