Metadata-Version: 2.1
Name: sanicargs
Version: 3.0.1
Summary: Parses query args or body parameters in sanic using type annotations
Home-page: https://github.com/trustpilot/python-sanicargs
Keywords: sanicargs,sanic,query,args,type annotations
Author: John Sutherland
Author-email: johns@trustpilot.com
Requires-Python: >=3.8,<4.0
Classifier: Development Status :: 5 - Production/Stable
Classifier: Intended Audience :: Developers
Classifier: Natural Language :: English
Classifier: Programming Language :: Python :: 3
Classifier: Programming Language :: Python :: 3.8
Classifier: Programming Language :: Python :: 3.9
Classifier: Programming Language :: Python :: 3.10
Classifier: Programming Language :: Python :: 3.11
Requires-Dist: ciso8601 (>=2.3.0,<3.0.0)
Requires-Dist: sanic (>=23.6.0,<24.0.0)
Project-URL: Repository, https://github.com/trustpilot/python-sanicargs
